BayesianMethodsForHackers/README.md
BayesianMethodsForHackers/__init__.py
BayesianMethodsForHackers/__main__.py
BayesianMethodsForHackers/file.epub
BayesianMethodsForHackers/index.html
BayesianMethodsForHackers/css/__init__.py
BayesianMethodsForHackers/css/annotations.css
BayesianMethodsForHackers/css/main.css
BayesianMethodsForHackers/css/normalize.css
BayesianMethodsForHackers/css/popup.css
BayesianMethodsForHackers/font/__init__.py
BayesianMethodsForHackers/font/fontello.eot
BayesianMethodsForHackers/font/fontello.svg
BayesianMethodsForHackers/font/fontello.ttf
BayesianMethodsForHackers/font/fontello.woff
BayesianMethodsForHackers/img/__init__.py
BayesianMethodsForHackers/img/annotator-glyph-sprite.png
BayesianMethodsForHackers/img/annotator-icon-sprite.png
BayesianMethodsForHackers/img/apple-touch-icon.png
BayesianMethodsForHackers/img/cancelfullscreen.png
BayesianMethodsForHackers/img/close.png
BayesianMethodsForHackers/img/fullscreen.png
BayesianMethodsForHackers/img/loader.gif
BayesianMethodsForHackers/img/menu-icon.png
BayesianMethodsForHackers/img/save.png
BayesianMethodsForHackers/img/saved.png
BayesianMethodsForHackers/img/settings-s.png
BayesianMethodsForHackers/img/settings.png
BayesianMethodsForHackers/img/star.png
BayesianMethodsForHackers/js/__init__.py
BayesianMethodsForHackers/js/epub.js
BayesianMethodsForHackers/js/epub.min.js
BayesianMethodsForHackers/js/epub.min.map
BayesianMethodsForHackers/js/hooks.min.js
BayesianMethodsForHackers/js/hooks.min.map
BayesianMethodsForHackers/js/reader.js
BayesianMethodsForHackers/js/reader.js.map
BayesianMethodsForHackers/js/reader.min.js
BayesianMethodsForHackers/js/reader.min.map
BayesianMethodsForHackers/js/hooks/__init__.py
BayesianMethodsForHackers/js/hooks/extensions/__init__.py
BayesianMethodsForHackers/js/hooks/extensions/highlight.js
BayesianMethodsForHackers/js/libs/__init__.py
BayesianMethodsForHackers/js/libs/jquery.min.js
BayesianMethodsForHackers/js/libs/localforage.min.js
bayesian_methods_for_hackers-2024.3.1.0.dist-info/METADATA
bayesian_methods_for_hackers-2024.3.1.0.dist-info/WHEEL
bayesian_methods_for_hackers-2024.3.1.0.dist-info/entry_points.txt
bayesian_methods_for_hackers-2024.3.1.0.dist-info/top_level.txt
bayesian_methods_for_hackers-2024.3.1.0.dist-info/RECORD
